crypto_com_facilitator_client/__init__.py
crypto_com_facilitator_client/integrations/__init__.py
crypto_com_facilitator_client/integrations/facilitator_api.py
crypto_com_facilitator_client/integrations/facilitator_interface.py
crypto_com_facilitator_client/integrations/facilitator_registry.py
crypto_com_facilitator_client/lib/__init__.py
crypto_com_facilitator_client/lib/client/__init__.py
crypto_com_facilitator_client/lib/client/index.py
crypto_com_facilitator_client/lib/utils/__init__.py
crypto_com_facilitator_client/lib/utils/payment_header.py
crypto_com_facilitator_client/lib/utils/payment_requirements.py
crypto_com_facilitator_client-1.0.3.dist-info/METADATA
crypto_com_facilitator_client-1.0.3.dist-info/WHEEL
crypto_com_facilitator_client-1.0.3.dist-info/licenses/LICENSE
crypto_com_facilitator_client-1.0.3.dist-info/RECORD
