Metadata-Version: 2.4
Name: crypto_com_facilitator_client
Version: 1.0.3
Summary: Official Cronos X402 Facilitator Python SDK
License: Apache-2.0
License-File: LICENSE
Author: Crypto.com
Requires-Python: >=3.9,<4.0.0
Classifier: License :: OSI Approved :: Apache Software License
Classifier: Programming Language :: Python :: 3
Classifier: Programming Language :: Python :: 3.9
Classifier: Programming Language :: Python :: 3.10
Classifier: Programming Language :: Python :: 3.11
Classifier: Programming Language :: Python :: 3.12
Classifier: Programming Language :: Python :: 3.13
Classifier: Programming Language :: Python :: 3.14
Requires-Dist: eth-account (>=0.10.0)
Requires-Dist: hexbytes (>=0.3.1)
Requires-Dist: requests (>=2.31.0)
Project-URL: Documentation, https://github.com/crypto-com/facilitator-client-py#readme
Project-URL: Homepage, https://facilitator.cronoslabs.org
Project-URL: Repository, https://github.com/crypto-com/facilitator-client-py
